[
 {
     "type": "title",
     "title": "Sample Title"
 },
 {
     "type": "path",
     "title": "Sample Path",
     "desc": "some path",
     "section": "generic",
     "key": "sample_path",
     "default": "/tmp",
     "behaviour": "SaveFile",
     "filter": "Images(*.png *.jpg);; Text files(*.txt)"
 },
 {
     "type": "options",
     "title": "sample options",
     "desc": "something",
     "section": "generic",
     "key": "sample_options",
     "options": {"option a": 1, "option b": 2, "option c": 3},
     "default": 3
 },
 {
     "type": "string",
     "title": "sample string",
     "desc": "a sinple string example",
     "section": "generic",
     "key": "sample_string",
     "default": "my string"
 },
 {
     "type": "bool",
     "title": "sample bool",
     "desc": "true or false",
     "section": "generic",
     "key": "sample_bool",
     "default": true
 },
 {
     "type": "numeric",
     "title": "sample integer",
     "desc": "some integer value",
     "section": "generic",
     "key": "sample_int",
     "decimals": 0,
     "default": 15
 },
 {
     "type": "numeric",
     "title": "sample double",
     "desc": "some double value",
     "section": "generic",
     "key": "sample_double",
     "default": 3.14
 }
]